{
  "job_id": "cf96a6f1-398b-49c6-b25f-4b7e1927dd0a",
  "preset": "draft",
  "pipeline_duration_ms": 446359,
  "stages": {
    "ingest": {
      "status": "ok",
      "duration_ms": 530,
      "metrics": {
        "slide_count": 27
      }
    },
    "evidence": {
      "status": "ok",
      "duration_ms": 4709,
      "metrics": {}
    },
    "render": {
      "status": "ok",
      "duration_ms": 71164,
      "metrics": {
        "slide_count": 27,
        "pdf_size": 334033
      }
    },
    "graph": {
      "status": "ok",
      "duration_ms": 4373,
      "metrics": {
        "unified_graph_count": 27
      }
    },
    "script": {
      "status": "ok",
      "duration_ms": 50,
      "metrics": {}
    },
    "script_en": {
      "status": "ok",
      "duration_ms": 50,
      "metrics": {}
    },
    "verify": {
      "status": "ok",
      "duration_ms": 86,
      "metrics": {}
    },
    "verify_en": {
      "status": "ok",
      "duration_ms": 86,
      "metrics": {}
    },
    "translate": {
      "status": "skipped",
      "duration_ms": 0,
      "metrics": {
        "reason": "not l2 or english"
      }
    },
    "translate_en": {
      "status": "skipped",
      "duration_ms": 0,
      "metrics": {
        "reason": "not l2 or english"
      }
    },
    "narrate": {
      "status": "ok",
      "duration_ms": 93417,
      "metrics": {
        "slides_rewritten": 27,
        "slides_total": 27,
        "slides_fallback": 0
      }
    },
    "narrate_en": {
      "status": "ok",
      "duration_ms": 93417,
      "metrics": {
        "slides_rewritten": 27,
        "slides_total": 27,
        "slides_fallback": 0
      }
    },
    "audio": {
      "status": "ok",
      "duration_ms": 176269,
      "metrics": {}
    },
    "audio_en": {
      "status": "ok",
      "duration_ms": 176269,
      "metrics": {}
    },
    "video": {
      "status": "ok",
      "duration_ms": 95751,
      "metrics": {
        "total_duration": 713.9241870000002
      }
    },
    "video_en": {
      "status": "ok",
      "duration_ms": 95751,
      "metrics": {
        "total_duration": 713.9241870000002
      }
    }
  },
  "created_at": "2026-04-05T19:23:48.576609+00:00Z"
}